lightning_transformers/__init__.py
lightning_transformers/callbacks/__init__.py
lightning_transformers/callbacks/sparseml.py
lightning_transformers/core/__init__.py
lightning_transformers/core/data.py
lightning_transformers/core/finetuning.py
lightning_transformers/core/iterable.py
lightning_transformers/core/loggers.py
lightning_transformers/core/model.py
lightning_transformers/core/utils.py
lightning_transformers/core/seq2seq/__init__.py
lightning_transformers/core/seq2seq/data.py
lightning_transformers/core/seq2seq/finetuning.py
lightning_transformers/core/seq2seq/model.py
lightning_transformers/core/seq2seq/utils.py
lightning_transformers/plugins/__init__.py
lightning_transformers/plugins/checkpoint.py
lightning_transformers/task/__init__.py
lightning_transformers/task/nlp/__init__.py
lightning_transformers/task/nlp/language_modeling/__init__.py
lightning_transformers/task/nlp/language_modeling/data.py
lightning_transformers/task/nlp/language_modeling/model.py
lightning_transformers/task/nlp/masked_language_modeling/__init__.py
lightning_transformers/task/nlp/masked_language_modeling/data.py
lightning_transformers/task/nlp/masked_language_modeling/model.py
lightning_transformers/task/nlp/multiple_choice/__init__.py
lightning_transformers/task/nlp/multiple_choice/data.py
lightning_transformers/task/nlp/multiple_choice/model.py
lightning_transformers/task/nlp/multiple_choice/utils.py
lightning_transformers/task/nlp/multiple_choice/datasets/__init__.py
lightning_transformers/task/nlp/multiple_choice/datasets/race/__init__.py
lightning_transformers/task/nlp/multiple_choice/datasets/race/data.py
lightning_transformers/task/nlp/multiple_choice/datasets/swag/__init__.py
lightning_transformers/task/nlp/multiple_choice/datasets/swag/data.py
lightning_transformers/task/nlp/question_answering/__init__.py
lightning_transformers/task/nlp/question_answering/data.py
lightning_transformers/task/nlp/question_answering/model.py
lightning_transformers-0.2.5.dist-info/LICENSE
lightning_transformers-0.2.5.dist-info/METADATA
lightning_transformers-0.2.5.dist-info/WHEEL
lightning_transformers-0.2.5.dist-info/top_level.txt
lightning_transformers-0.2.5.dist-info/RECORD
