Metadata-Version: 2.1
Name: lightning-transformers
Version: 0.2.5
Summary: Lightning Transformers.
Home-page: https://github.com/Lightning-AI/lightning-transformers
Download-URL: https://github.com/Lightning-AI/lightning-transformers
Author: Lightning AI et al.
Author-email: pytorch@lightning.ai
License: Apache-2.0
Project-URL: Bug Tracker, https://github.com/Lightning-AI/lightning-transformers/issues
Project-URL: Documentation, https://lightning-transformers.readthedocs.io/en/stable/
Project-URL: Source Code, https://github.com/Lightning-AI/lightning-transformers
Keywords: deep learning,pytorch,AI
Classifier: Environment :: Console
Classifier: Natural Language :: English
Classifier: Development Status :: 4 - Beta
Classifier: Intended Audience :: Developers
Classifier: Topic :: Scientific/Engineering :: Artificial Intelligence
Classifier: Topic :: Scientific/Engineering :: Image Recognition
Classifier: Topic :: Scientific/Engineering :: Information Analysis
Classifier: License :: OSI Approved :: Apache Software License
Classifier: Operating System :: OS Independent
Classifier: Programming Language :: Python :: 3
Classifier: Programming Language :: Python :: 3.7
Classifier: Programming Language :: Python :: 3.8
Classifier: Programming Language :: Python :: 3.9
Classifier: Programming Language :: Python :: 3.10
Requires-Python: >=3.7
License-File: LICENSE
Requires-Dist: pytorch-lightning (>=1.7.0)
Requires-Dist: transformers (>=4.21.0)
Requires-Dist: datasets (>2.0.0)
Requires-Dist: sentencepiece (>=0.1.96)
Requires-Dist: torchmetrics[text] (>=0.8.0)
Requires-Dist: Pillow (>=9.0.0)
Provides-Extra: extra
Requires-Dist: lightning-bolts (>=0.6.0) ; extra == 'extra'
Requires-Dist: deepspeed (>=0.6.0) ; extra == 'extra'
Requires-Dist: accelerate (>=0.11.0) ; extra == 'extra'
